google/cloud/deploy/__init__.py
google/cloud/deploy/gapic_version.py
google/cloud/deploy/py.typed
google/cloud/deploy_v1/__init__.py
google/cloud/deploy_v1/gapic_metadata.json
google/cloud/deploy_v1/gapic_version.py
google/cloud/deploy_v1/py.typed
google/cloud/deploy_v1/services/__init__.py
google/cloud/deploy_v1/services/cloud_deploy/__init__.py
google/cloud/deploy_v1/services/cloud_deploy/async_client.py
google/cloud/deploy_v1/services/cloud_deploy/client.py
google/cloud/deploy_v1/services/cloud_deploy/pagers.py
google/cloud/deploy_v1/services/cloud_deploy/transports/__init__.py
google/cloud/deploy_v1/services/cloud_deploy/transports/base.py
google/cloud/deploy_v1/services/cloud_deploy/transports/grpc.py
google/cloud/deploy_v1/services/cloud_deploy/transports/grpc_asyncio.py
google/cloud/deploy_v1/services/cloud_deploy/transports/rest.py
google/cloud/deploy_v1/services/cloud_deploy/transports/rest_base.py
google/cloud/deploy_v1/types/__init__.py
google/cloud/deploy_v1/types/automation_payload.py
google/cloud/deploy_v1/types/automationrun_payload.py
google/cloud/deploy_v1/types/cloud_deploy.py
google/cloud/deploy_v1/types/customtargettype_notification_payload.py
google/cloud/deploy_v1/types/deliverypipeline_notification_payload.py
google/cloud/deploy_v1/types/deploypolicy_evaluation_payload.py
google/cloud/deploy_v1/types/deploypolicy_notification_payload.py
google/cloud/deploy_v1/types/jobrun_notification_payload.py
google/cloud/deploy_v1/types/log_enums.py
google/cloud/deploy_v1/types/release_notification_payload.py
google/cloud/deploy_v1/types/release_render_payload.py
google/cloud/deploy_v1/types/rollout_notification_payload.py
google/cloud/deploy_v1/types/rollout_update_payload.py
google/cloud/deploy_v1/types/target_notification_payload.py
google_cloud_deploy-2.8.0.dist-info/licenses/LICENSE
google_cloud_deploy-2.8.0.dist-info/METADATA
google_cloud_deploy-2.8.0.dist-info/WHEEL
google_cloud_deploy-2.8.0.dist-info/top_level.txt
google_cloud_deploy-2.8.0.dist-info/RECORD
